{
  "antigen": "KVFGRCELAAAMKRHGLDNYRGYSLGNWVCAAKFESNFNTQATNRNTDGSTDYGILQINSRWWCNDGRTPGSRNLCNIPCSALLSSDITASVNCAKKIVSDGNGMNAWVAWRNRCKGTDVQAWIRGCRL",
  "seed_cdr3": "ARERDYRLDY",
  "esm": "t12_35M",
  "checkpoint": "score_model.pt",
  "steps": 200,
  "beam": 50,
  "k_mut": 1,
  "keep_top": 50,
  "embed_batch": 64,
  "clusters": 12,
  "out_folder": "runs",
  "pairs_csv": "data/antigen_cdr3_pairs.csv",
  "epochs": 20,
  "train_batch": 128,
  "threads": 2,
  "use_gpu": true,
  "hard_neg": true,
  "hn_factor": 1,
  "pos_mult": 1,
  "last_raw": "runs\\opt_20251029_225649.csv",
  "last_filtered": "runs\\opt_20251029_225649_filtered.csv",
  "last_panel": "runs\\opt_20251029_225649_filtered_panel.csv"
}